ml_pool/__init__.py
ml_pool/config.py
ml_pool/custom_types.py
ml_pool/exceptions.py
ml_pool/logger.py
ml_pool/messages.py
ml_pool/pool.py
ml_pool/utils.py
ml_pool/worker.py
tests/__init__.py
tests/test_pool.py
tests/test_worker.py
MLPool-0.1.0.dist-info/METADATA
MLPool-0.1.0.dist-info/WHEEL
MLPool-0.1.0.dist-info/top_level.txt
MLPool-0.1.0.dist-info/RECORD
