Metadata-Version: 2.1
Name: MLPool
Version: 0.1.0
Summary: Offloading CPU intensive model scoring to a pool of workers
Author: ET
Author-email: <titov.1994@list.ru>
Keywords: python,machine learning,multiprocessing
Classifier: Intended Audience :: Developers
Classifier: Programming Language :: Python :: 3
Classifier: Operating System :: Unix
Classifier: Operating System :: MacOS :: MacOS X
Classifier: Operating System :: Microsoft :: Windows
